{
  "providerName": "Microsoft.Windows.Print.MS3DPrintShellExtension",
  "guid": "{78F5CB32-81C4-476B-A93B-F5D90226CE9B}",
  "os": "WindowsServer2025",
  "binaryCount": 1,
  "binaries": [
    "ms3dthumbnailprovider.dll"
  ],
  "uniqueEventCount": 5,
  "events": [
    {
      "eventName": "ActivityError",
      "variantCount": 2,
      "variants": [
        {
          "level": 2,
          "keyword": "0x600000000000",
          "fields": [
            "PartA_PrivTags:UInt64",
            "wilActivity:Struct(NTStatus)",
            "hresult:UInt32",
            "fileName:AnsiString",
            "lineNumber:UInt32",
            "module:AnsiString",
            "failureType:UInt32",
            "message:UnicodeString",
            "threadId:UInt32",
            "callContext:AnsiString",
            "originatingContextId:UInt32",
            "originatingContextName:AnsiString",
            "originatingContextMessage:UnicodeString",
            "currentContextId:UInt32",
            "currentContextName:AnsiString",
            "currentContextMessage:UnicodeString"
          ],
          "callers": [
            {
              "binary": "ms3dthumbnailprovider.dll",
              "function": "?NotifyFailure@?$ActivityBase@VMS3DPrintShellExtension@@$00$0EAAAAAAAAAAA@$04$0A@U_TlgReflectorTag_Param0IsProviderType@@@wil@@UEAA_NAEBUFailureInfo@2@@Z",
              "ea": "0x180007bd1",
              "confidence": "SingleProvider"
            }
          ]
        },
        {
          "level": 2,
          "keyword": "0x400000000000",
          "fields": [
            "PartA_PrivTags:UInt64",
            "wilActivity:Struct(Signed)",
            "hresult:UInt32",
            "fileName:AnsiString",
            "lineNumber:UInt32",
            "module:AnsiString",
            "failureType:UInt32",
            "message:UnicodeString",
            "threadId:UInt32",
            "callContext:AnsiString",
            "originatingContextId:UInt32",
            "originatingContextName:AnsiString",
            "originatingContextMessage:UnicodeString",
            "currentContextId:UInt32",
            "currentContextName:AnsiString",
            "currentContextMessage:UnicodeString",
            "failureId:UInt32",
            "failureCount:UInt32",
            "function:AnsiString"
          ],
          "callers": [
            {
              "binary": "ms3dthumbnailprovider.dll",
              "function": "?NotifyFailure@?$ActivityBase@VMS3DPrintShellExtension@@$00$0EAAAAAAAAAAA@$04$0A@U_TlgReflectorTag_Param0IsProviderType@@@wil@@UEAA_NAEBUFailureInfo@2@@Z",
              "ea": "0x180007d24",
              "confidence": "SingleProvider"
            }
          ]
        }
      ],
      "fieldSummary": [
        {
          "fieldName": "PartA_PrivTags",
          "type": "UInt64",
          "seenIn": [
            "ms3dthumbnailprovider.dll"
          ]
        },
        {
          "fieldName": "callContext",
          "type": "AnsiString",
          "seenIn": [
            "ms3dthumbnailprovider.dll"
          ]
        },
        {
          "fieldName": "currentContextId",
          "type": "UInt32",
          "seenIn": [
            "ms3dthumbnailprovider.dll"
          ]
        },
        {
          "fieldName": "currentContextMessage",
          "type": "UnicodeString",
          "seenIn": [
            "ms3dthumbnailprovider.dll"
          ]
        },
        {
          "fieldName": "currentContextName",
          "type": "AnsiString",
          "seenIn": [
            "ms3dthumbnailprovider.dll"
          ]
        },
        {
          "fieldName": "failureCount",
          "type": "UInt32",
          "seenIn": [
            "ms3dthumbnailprovider.dll"
          ]
        },
        {
          "fieldName": "failureId",
          "type": "UInt32",
          "seenIn": [
            "ms3dthumbnailprovider.dll"
          ]
        },
        {
          "fieldName": "failureType",
          "type": "UInt32",
          "seenIn": [
            "ms3dthumbnailprovider.dll"
          ]
        },
        {
          "fieldName": "fileName",
          "type": "AnsiString",
          "seenIn": [
            "ms3dthumbnailprovider.dll"
          ]
        },
        {
          "fieldName": "function",
          "type": "AnsiString",
          "seenIn": [
            "ms3dthumbnailprovider.dll"
          ]
        },
        {
          "fieldName": "hresult",
          "type": "UInt32",
          "seenIn": [
            "ms3dthumbnailprovider.dll"
          ]
        },
        {
          "fieldName": "lineNumber",
          "type": "UInt32",
          "seenIn": [
            "ms3dthumbnailprovider.dll"
          ]
        },
        {
          "fieldName": "message",
          "type": "UnicodeString",
          "seenIn": [
            "ms3dthumbnailprovider.dll"
          ]
        },
        {
          "fieldName": "module",
          "type": "AnsiString",
          "seenIn": [
            "ms3dthumbnailprovider.dll"
          ]
        },
        {
          "fieldName": "originatingContextId",
          "type": "UInt32",
          "seenIn": [
            "ms3dthumbnailprovider.dll"
          ]
        },
        {
          "fieldName": "originatingContextMessage",
          "type": "UnicodeString",
          "seenIn": [
            "ms3dthumbnailprovider.dll"
          ]
        },
        {
          "fieldName": "originatingContextName",
          "type": "AnsiString",
          "seenIn": [
            "ms3dthumbnailprovider.dll"
          ]
        },
        {
          "fieldName": "threadId",
          "type": "UInt32",
          "seenIn": [
            "ms3dthumbnailprovider.dll"
          ]
        },
        {
          "fieldName": "wilActivity",
          "type": "Struct(NTStatus)",
          "seenIn": [
            "ms3dthumbnailprovider.dll"
          ]
        },
        {
          "fieldName": "wilActivity",
          "type": "Struct(Signed)",
          "seenIn": [
            "ms3dthumbnailprovider.dll"
          ]
        }
      ]
    },
    {
      "eventName": "ActivityIntermediateStop",
      "variantCount": 1,
      "variants": [
        {
          "level": 5,
          "keyword": "0x400000000000",
          "fields": [
            "PartA_PrivTags:UInt64",
            "wilActivity:Struct(String)",
            "hresult:UInt32",
            "threadId:UInt32"
          ],
          "callers": [
            {
              "binary": "ms3dthumbnailprovider.dll",
              "function": "?Stop@?$ActivityBase@VMS3DPrintShellExtension@@$00$0EAAAAAAAAAAA@$04$0A@U_TlgReflectorTag_Param0IsProviderType@@@wil@@QEAAXJ@Z",
              "ea": "0x180009624",
              "confidence": "SingleProvider"
            }
          ]
        }
      ],
      "fieldSummary": [
        {
          "fieldName": "PartA_PrivTags",
          "type": "UInt64",
          "seenIn": [
            "ms3dthumbnailprovider.dll"
          ]
        },
        {
          "fieldName": "hresult",
          "type": "UInt32",
          "seenIn": [
            "ms3dthumbnailprovider.dll"
          ]
        },
        {
          "fieldName": "threadId",
          "type": "UInt32",
          "seenIn": [
            "ms3dthumbnailprovider.dll"
          ]
        },
        {
          "fieldName": "wilActivity",
          "type": "Struct(String)",
          "seenIn": [
            "ms3dthumbnailprovider.dll"
          ]
        }
      ]
    },
    {
      "eventName": "ActivityStoppedAutomatically",
      "variantCount": 1,
      "variants": [
        {
          "level": 5,
          "keyword": "0x400000000000",
          "fields": [],
          "callers": [
            {
              "binary": "ms3dthumbnailprovider.dll",
              "function": "??$_tlgWriteActivityAutoStop@$0EAAAAAAAAAAA@$04@@YAXPEBU_tlgProvider_t@@PEBU_GUID@@@Z",
              "ea": "0x1800053da",
              "confidence": "SingleProvider"
            }
          ]
        }
      ],
      "fieldSummary": []
    },
    {
      "eventName": "FallbackError",
      "variantCount": 2,
      "variants": [
        {
          "level": 2,
          "keyword": "0x200000000000",
          "fields": [
            "PartA_PrivTags:UInt64",
            "PartA_PrivTags:UInt64",
            "wilResult:Struct(NTStatus)",
            "hresult:UInt32",
            "fileName:AnsiString",
            "lineNumber:UInt32",
            "module:AnsiString",
            "failureType:UInt32",
            "message:UnicodeString",
            "threadId:UInt32",
            "callContext:AnsiString",
            "originatingContextId:UInt32",
            "originatingContextName:AnsiString",
            "originatingContextMessage:UnicodeString",
            "currentContextId:UInt32",
            "currentContextName:AnsiString",
            "currentContextMessage:UnicodeString"
          ],
          "callers": [
            {
              "binary": "ms3dthumbnailprovider.dll",
              "function": "?ReportTelemetryFailure@TraceLoggingProvider@wil@@IEAAXAEBUFailureInfo@2@@Z",
              "ea": "0x180008717",
              "confidence": "SingleProvider"
            }
          ]
        },
        {
          "level": 2,
          "keyword": "0x0",
          "fields": [
            "PartA_PrivTags:UInt64",
            "wilResult:Struct(Signed)",
            "hresult:UInt32",
            "fileName:AnsiString",
            "lineNumber:UInt32",
            "module:AnsiString",
            "failureType:UInt32",
            "message:UnicodeString",
            "threadId:UInt32",
            "callContext:AnsiString",
            "originatingContextId:UInt32",
            "originatingContextName:AnsiString",
            "originatingContextMessage:UnicodeString",
            "currentContextId:UInt32",
            "currentContextName:AnsiString",
            "currentContextMessage:UnicodeString",
            "failureId:UInt32",
            "failureCount:UInt32",
            "function:AnsiString"
          ],
          "callers": [
            {
              "binary": "ms3dthumbnailprovider.dll",
              "function": "?ReportTraceLoggingFailure@TraceLoggingProvider@wil@@IEAAXAEBUFailureInfo@2@@Z",
              "ea": "0x18000886a",
              "confidence": "SingleProvider"
            }
          ]
        }
      ],
      "fieldSummary": [
        {
          "fieldName": "PartA_PrivTags",
          "type": "UInt64",
          "seenIn": [
            "ms3dthumbnailprovider.dll"
          ]
        },
        {
          "fieldName": "callContext",
          "type": "AnsiString",
          "seenIn": [
            "ms3dthumbnailprovider.dll"
          ]
        },
        {
          "fieldName": "currentContextId",
          "type": "UInt32",
          "seenIn": [
            "ms3dthumbnailprovider.dll"
          ]
        },
        {
          "fieldName": "currentContextMessage",
          "type": "UnicodeString",
          "seenIn": [
            "ms3dthumbnailprovider.dll"
          ]
        },
        {
          "fieldName": "currentContextName",
          "type": "AnsiString",
          "seenIn": [
            "ms3dthumbnailprovider.dll"
          ]
        },
        {
          "fieldName": "failureCount",
          "type": "UInt32",
          "seenIn": [
            "ms3dthumbnailprovider.dll"
          ]
        },
        {
          "fieldName": "failureId",
          "type": "UInt32",
          "seenIn": [
            "ms3dthumbnailprovider.dll"
          ]
        },
        {
          "fieldName": "failureType",
          "type": "UInt32",
          "seenIn": [
            "ms3dthumbnailprovider.dll"
          ]
        },
        {
          "fieldName": "fileName",
          "type": "AnsiString",
          "seenIn": [
            "ms3dthumbnailprovider.dll"
          ]
        },
        {
          "fieldName": "function",
          "type": "AnsiString",
          "seenIn": [
            "ms3dthumbnailprovider.dll"
          ]
        },
        {
          "fieldName": "hresult",
          "type": "UInt32",
          "seenIn": [
            "ms3dthumbnailprovider.dll"
          ]
        },
        {
          "fieldName": "lineNumber",
          "type": "UInt32",
          "seenIn": [
            "ms3dthumbnailprovider.dll"
          ]
        },
        {
          "fieldName": "message",
          "type": "UnicodeString",
          "seenIn": [
            "ms3dthumbnailprovider.dll"
          ]
        },
        {
          "fieldName": "module",
          "type": "AnsiString",
          "seenIn": [
            "ms3dthumbnailprovider.dll"
          ]
        },
        {
          "fieldName": "originatingContextId",
          "type": "UInt32",
          "seenIn": [
            "ms3dthumbnailprovider.dll"
          ]
        },
        {
          "fieldName": "originatingContextMessage",
          "type": "UnicodeString",
          "seenIn": [
            "ms3dthumbnailprovider.dll"
          ]
        },
        {
          "fieldName": "originatingContextName",
          "type": "AnsiString",
          "seenIn": [
            "ms3dthumbnailprovider.dll"
          ]
        },
        {
          "fieldName": "threadId",
          "type": "UInt32",
          "seenIn": [
            "ms3dthumbnailprovider.dll"
          ]
        },
        {
          "fieldName": "wilResult",
          "type": "Struct(NTStatus)",
          "seenIn": [
            "ms3dthumbnailprovider.dll"
          ]
        },
        {
          "fieldName": "wilResult",
          "type": "Struct(Signed)",
          "seenIn": [
            "ms3dthumbnailprovider.dll"
          ]
        }
      ]
    },
    {
      "eventName": "RightClickToPrint",
      "variantCount": 3,
      "variants": [
        {
          "level": 5,
          "keyword": "0x400000000000",
          "fields": [
            "PartA_PrivTags:UInt64",
            "wilActivity:Struct(NoPrint)",
            "threadId:UInt32"
          ],
          "callers": [
            {
              "binary": "ms3dthumbnailprovider.dll",
              "function": "?StartActivity@RightClickToPrint@ShellExtensionTelemetry@@QEAAXXZ",
              "ea": "0x180009456",
              "confidence": "SingleProvider"
            }
          ]
        },
        {
          "level": 5,
          "keyword": "0x400000000000",
          "fields": [
            "PartA_PrivTags:UInt64",
            "PartA_PrivTags:UInt64",
            "wilActivity:Struct(NTStatus)",
            "hresult:UInt32",
            "fileName:AnsiString",
            "lineNumber:UInt32",
            "module:AnsiString",
            "failureType:UInt32",
            "message:UnicodeString",
            "threadId:UInt32",
            "callContext:AnsiString",
            "originatingContextId:UInt32",
            "originatingContextName:AnsiString",
            "originatingContextMessage:UnicodeString",
            "currentContextId:UInt32",
            "currentContextName:AnsiString",
            "currentContextMessage:UnicodeString"
          ],
          "callers": [
            {
              "binary": "ms3dthumbnailprovider.dll",
              "function": "?StopActivity@RightClickToPrint@ShellExtensionTelemetry@@MEAAXXZ",
              "ea": "0x18000979b",
              "confidence": "SingleProvider"
            }
          ]
        },
        {
          "level": 5,
          "keyword": "0x400000000000",
          "fields": [
            "PartA_PrivTags:UInt64",
            "wilActivity:Struct(String)",
            "hresult:UInt32",
            "threadId:UInt32"
          ],
          "callers": [
            {
              "binary": "ms3dthumbnailprovider.dll",
              "function": "?StopActivity@RightClickToPrint@ShellExtensionTelemetry@@MEAAXXZ",
              "ea": "0x180009930",
              "confidence": "SingleProvider"
            }
          ]
        }
      ],
      "fieldSummary": [
        {
          "fieldName": "PartA_PrivTags",
          "type": "UInt64",
          "seenIn": [
            "ms3dthumbnailprovider.dll"
          ]
        },
        {
          "fieldName": "callContext",
          "type": "AnsiString",
          "seenIn": [
            "ms3dthumbnailprovider.dll"
          ]
        },
        {
          "fieldName": "currentContextId",
          "type": "UInt32",
          "seenIn": [
            "ms3dthumbnailprovider.dll"
          ]
        },
        {
          "fieldName": "currentContextMessage",
          "type": "UnicodeString",
          "seenIn": [
            "ms3dthumbnailprovider.dll"
          ]
        },
        {
          "fieldName": "currentContextName",
          "type": "AnsiString",
          "seenIn": [
            "ms3dthumbnailprovider.dll"
          ]
        },
        {
          "fieldName": "failureType",
          "type": "UInt32",
          "seenIn": [
            "ms3dthumbnailprovider.dll"
          ]
        },
        {
          "fieldName": "fileName",
          "type": "AnsiString",
          "seenIn": [
            "ms3dthumbnailprovider.dll"
          ]
        },
        {
          "fieldName": "hresult",
          "type": "UInt32",
          "seenIn": [
            "ms3dthumbnailprovider.dll"
          ]
        },
        {
          "fieldName": "lineNumber",
          "type": "UInt32",
          "seenIn": [
            "ms3dthumbnailprovider.dll"
          ]
        },
        {
          "fieldName": "message",
          "type": "UnicodeString",
          "seenIn": [
            "ms3dthumbnailprovider.dll"
          ]
        },
        {
          "fieldName": "module",
          "type": "AnsiString",
          "seenIn": [
            "ms3dthumbnailprovider.dll"
          ]
        },
        {
          "fieldName": "originatingContextId",
          "type": "UInt32",
          "seenIn": [
            "ms3dthumbnailprovider.dll"
          ]
        },
        {
          "fieldName": "originatingContextMessage",
          "type": "UnicodeString",
          "seenIn": [
            "ms3dthumbnailprovider.dll"
          ]
        },
        {
          "fieldName": "originatingContextName",
          "type": "AnsiString",
          "seenIn": [
            "ms3dthumbnailprovider.dll"
          ]
        },
        {
          "fieldName": "threadId",
          "type": "UInt32",
          "seenIn": [
            "ms3dthumbnailprovider.dll"
          ]
        },
        {
          "fieldName": "wilActivity",
          "type": "Struct(NTStatus)",
          "seenIn": [
            "ms3dthumbnailprovider.dll"
          ]
        },
        {
          "fieldName": "wilActivity",
          "type": "Struct(NoPrint)",
          "seenIn": [
            "ms3dthumbnailprovider.dll"
          ]
        },
        {
          "fieldName": "wilActivity",
          "type": "Struct(String)",
          "seenIn": [
            "ms3dthumbnailprovider.dll"
          ]
        }
      ]
    }
  ]
}